tetherhelix_grpc/__init__.py
tetherhelix_grpc/admin_pb2.py
tetherhelix_grpc/admin_pb2.pyi
tetherhelix_grpc/admin_pb2_grpc.py
tetherhelix_grpc/globals_pb2.py
tetherhelix_grpc/globals_pb2.pyi
tetherhelix_grpc/globals_pb2_grpc.py
tetherhelix_grpc/tetherbot_pb2.py
tetherhelix_grpc/tetherbot_pb2.pyi
tetherhelix_grpc/tetherbot_pb2_grpc.py
tetherhelix_grpc/transaction_pb2.py
tetherhelix_grpc/transaction_pb2.pyi
tetherhelix_grpc/transaction_pb2_grpc.py
tetherhelix_grpc-0.3.0.dist-info/LICENSE
tetherhelix_grpc-0.3.0.dist-info/METADATA
tetherhelix_grpc-0.3.0.dist-info/WHEEL
tetherhelix_grpc-0.3.0.dist-info/top_level.txt
tetherhelix_grpc-0.3.0.dist-info/RECORD
