Metadata-Version: 2.2
Name: tetherhelix_grpc
Version: 0.3.0
Summary: Generated gRPC Python package
Author-email: TetherHelix <tetherhelixofficial@example.com>
License: BSD-3-Clause
Classifier: Programming Language :: Python :: 3
Requires-Python: >=3.6
License-File: LICENSE
Requires-Dist: grpcio
Requires-Dist: grpcio-tools
